pytest_poo.py
pytest_poo-1.0.dist-info/LICENSE
pytest_poo-1.0.dist-info/METADATA
pytest_poo-1.0.dist-info/WHEEL
pytest_poo-1.0.dist-info/entry_points.txt
pytest_poo-1.0.dist-info/top_level.txt
pytest_poo-1.0.dist-info/RECORD
