Metadata-Version: 2.1
Name: pytest-poo
Version: 1.0
Summary: Visualize your crappy tests
Home-page: http://github.com/pelme/pytest-poo
Author: Andreas Pelme
Author-email: andreas@pelme.se
Maintainer: Andreas Pelme
Maintainer-email: andreas@pelme.se
License: UNKNOWN
Platform: UNKNOWN
Classifier: Development Status :: 5 - Production/Stable
Classifier: Intended Audience :: Developers
Classifier: License :: OSI Approved :: BSD License
Classifier: Operating System :: OS Independent
Classifier: Programming Language :: Python
Classifier: Topic :: Software Development :: Testing
Classifier: Programming Language :: Python :: 2.5
Classifier: Programming Language :: Python :: 2.6
Classifier: Programming Language :: Python :: 2.7
Classifier: Programming Language :: Python :: 3.2
Classifier: Programming Language :: Python :: 3.3
Requires-Dist: pytest (>=2.3.4)
